jasypt4py/__init__.py
jasypt4py/encryptor.py
jasypt4py/exceptions.py
jasypt4py/generator.py
jasypt4py-0.0.3.dist-info/DESCRIPTION.rst
jasypt4py-0.0.3.dist-info/METADATA
jasypt4py-0.0.3.dist-info/RECORD
jasypt4py-0.0.3.dist-info/WHEEL
jasypt4py-0.0.3.dist-info/metadata.json
jasypt4py-0.0.3.dist-info/top_level.txt
