Metadata-Version: 2.0
Name: jasypt4py
Version: 0.0.3
Summary: Cipher functions that produce Jasypt/Bouncycastle compatible password encryption.
Home-page: https://github.com/fareliner/jasypt4py
Author: Niels Bertram
Author-email: nielsbne@gmail.com
License: Apache License 2.0
Keywords: jasypt bouncycastle AES crypto SHA256
Platform: UNKNOWN
Classifier: Development Status :: 3 - Alpha
Classifier: Intended Audience :: Developers
Classifier: Topic :: Software Development :: Build Tools
Classifier: Topic :: System :: Software Distribution
Classifier: Topic :: System :: Systems Administration
Classifier: License :: OSI Approved :: Apache Software License
Classifier: Natural Language :: English
Classifier: Programming Language :: Python :: 2
Classifier: Programming Language :: Python :: 2.7
Classifier: Programming Language :: Python :: 3
Classifier: Programming Language :: Python :: 3.3
Classifier: Programming Language :: Python :: 3.4
Classifier: Programming Language :: Python :: 3.5
Classifier: Programming Language :: Python :: 2
Classifier: Programming Language :: Python :: 2.7
Classifier: Programming Language :: Python :: 3
Requires-Dist: pycrypto
